redparser/__init__.py
redparser/__main__.py
redparser/argparser.py
redparser/arguments.py
redparser/cmd_action.py
redparser/constants.py
redparser/exceptions.py
redparser/highlight.py
redparser/memory_parser.py
redparser/mmap_parser.py
redparser/parser.py
redparser/redparser.py
redparser/validator.py
redparser-2.0.0.dist-info/METADATA
redparser-2.0.0.dist-info/WHEEL
redparser-2.0.0.dist-info/entry_points.txt
redparser-2.0.0.dist-info/top_level.txt
redparser-2.0.0.dist-info/RECORD
