Metadata-Version: 2.1
Name: redparser
Version: 2.0.0
Summary: Simple Python library to use parse log files
Home-page: UNKNOWN
Author: mtclinton
Author-email: max@mtclinton.com
License: UNKNOWN
Platform: UNKNOWN
Classifier: Programming Language :: Python :: 3
Classifier: Operating System :: OS Independent
Requires-Python: >=3.5
